CHANGES.txt
LICENSE.txt
MANIFEST.in
README.rst
monthdelta.py
setup.cfg
setup.py
MonthDelta.egg-info/PKG-INFO
MonthDelta.egg-info/SOURCES.txt
MonthDelta.egg-info/dependency_links.txt
MonthDelta.egg-info/top_level.txt
doc/source/index.rst