Metadata-Version: 1.1
Name: MonthDelta
Version: 1.0b
Summary: date computations with months
Home-page: http://pypi.python.org/pypi/MonthDelta
Author: Jess Austin
Author-email: jess.austin@gmail.com
License: MIT
Platform: UNKNOWN
Classifier: Development Status :: 5 - Production/Stable
Classifier: License :: OSI Approved :: MIT License
Classifier: Operating System :: OS Independent
Classifier: Programming Language :: Python :: 2
Classifier: Programming Language :: Python :: 3
Provides: monthdelta
